pygpsd/__init__.py
pygpsd/type/__init__.py
pygpsd/type/data.py
pygpsd/type/ecef.py
pygpsd/type/fix.py
pygpsd/type/geo.py
pygpsd/type/health.py
pygpsd/type/satellite.py
pygpsd/type/time.py
pygpsd-1.1.4.dist-info/METADATA
pygpsd-1.1.4.dist-info/WHEEL
pygpsd-1.1.4.dist-info/licenses/LICENSE
pygpsd-1.1.4.dist-info/RECORD
